{
  "unversionedId": "Documentation/WDI/Prerequisites",
  "id": "Documentation/WDI/Prerequisites",
  "title": "Prerequisites-WDI",
  "description": "Before getting started with WDI, there are some prerequisites to ensure the correct outcome:",
  "source": "@site/docs/Documentation/WDI/Prerequisites.md",
  "sourceDirName": "Documentation/WDI",
  "slug": "/Documentation/WDI/Prerequisites",
  "permalink": "/my-docusaurus-web/docs/Documentation/WDI/Prerequisites",
  "draft": false,
  "tags": [],
  "version": "current",
  "frontMatter": {},
  "sidebar": "documentationSidebar",
  "previous": {
    "title": "Projectstructure",
    "permalink": "/my-docusaurus-web/docs/Documentation/MindMap/Projectstructure"
  },
  "next": {
    "title": "Description",
    "permalink": "/my-docusaurus-web/docs/Documentation/WDI/"
  }
}